objtojson/__init__.py
objtojson/serialize.py
objtojson-0.5.0.dist-info/METADATA
objtojson-0.5.0.dist-info/WHEEL
objtojson-0.5.0.dist-info/top_level.txt
objtojson-0.5.0.dist-info/RECORD
