Metadata-Version: 2.1
Name: objtojson
Version: 0.5.0
Summary: Object to JSON serialization with none to minimal need for custom declarations
Home-page: https://github.com/joergrs/object-to-json
Author: Joerg Schroeter
License: MIT
Platform: UNKNOWN
Classifier: License :: OSI Approved :: MIT License
Classifier: Programming Language :: Python
Classifier: Programming Language :: Python :: 3
Classifier: Operating System :: OS Independent
Requires-Python: >=3.6
